supportdata/__init__.py
supportdata/supportdata.py
supportdata-0.1.3.dist-info/AUTHORS.rst
supportdata-0.1.3.dist-info/LICENSE
supportdata-0.1.3.dist-info/METADATA
supportdata-0.1.3.dist-info/WHEEL
supportdata-0.1.3.dist-info/top_level.txt
supportdata-0.1.3.dist-info/RECORD
