Metadata-Version: 2.1
Name: supportdata
Version: 0.1.3
Summary: Download support data for Python pacakges, like sample data for tests and binary databases.
Home-page: https://github.com/castelao/supportdata
Author: Guilherme Castelão
Author-email: guilherme@castelao.net
License: BSD license
Keywords: supportdata
Platform: UNKNOWN
Classifier: Development Status :: 4 - Beta
Classifier: Intended Audience :: Developers
Classifier: License :: OSI Approved :: BSD License
Classifier: Natural Language :: English
Classifier: Programming Language :: Python :: 2
Classifier: Programming Language :: Python :: 2.7
Classifier: Programming Language :: Python :: 3
Classifier: Programming Language :: Python :: 3.5
Classifier: Programming Language :: Python :: 3.6
Requires-Dist: six (>=1.5.2)
Requires-Dist: filelock (>=2.0)
